ftThanos/ft_connector.py
ftThanos/google_connector.py
ftThanos/log.py
ftThanos/notion_connector.py
ftThanos/notion_get_properties.py
ftThanos/notion_update_properties.py
ftThanos-0.2.2.dist-info/METADATA
ftThanos-0.2.2.dist-info/WHEEL
ftThanos-0.2.2.dist-info/top_level.txt
ftThanos-0.2.2.dist-info/RECORD
