Metadata-Version: 2.1
Name: ftThanos
Version: 0.2.2
Summary: A client for 42 API
Home-page: UNKNOWN
Author: Thanos 42
Author-email: thanos@42paris.fr
License: UNKNOWN
Platform: UNKNOWN
Requires-Dist: python-dotenv
Requires-Dist: requests
